taffy/__init__.py
taffy/_taffy_build.py
taffy/_taffy_cffi.abi3.so
taffy/lib.py
taffy/ml.py
taffy/newick.py
taffy/wiggle.py
taffy/impl/alignment_block.c
taffy/impl/line_iterator.c
taffy/impl/maf.c
taffy/impl/merge_adjacent_alignments.c
taffy/impl/ond.c
taffy/impl/paf.c
taffy/impl/prefix_sort.c
taffy/impl/taf.c
taffy/impl/tai.c
taffy/impl/wiggle.c
taffy/inc/line_iterator.h
taffy/inc/ond.h
taffy/inc/taf.h
taffy/inc/tai.h
taffy/submodules/abPOA/include/abpoa.h
taffy/submodules/abPOA/include/simd_instruction.h
taffy/submodules/sonLib/C/impl/avl.c
taffy/submodules/sonLib/C/impl/bioioC.c
taffy/submodules/sonLib/C/impl/commonC.c
taffy/submodules/sonLib/C/impl/fastCMaths.c
taffy/submodules/sonLib/C/impl/hashTableC.c
taffy/submodules/sonLib/C/impl/hashTableC_itr.c
taffy/submodules/sonLib/C/impl/jsmn.c
taffy/submodules/sonLib/C/impl/lz4.c
taffy/submodules/sonLib/C/impl/lz4.h
taffy/submodules/sonLib/C/impl/lz4hc.c
taffy/submodules/sonLib/C/impl/lz4hc.h
taffy/submodules/sonLib/C/impl/pairwiseAlignment.c
taffy/submodules/sonLib/C/impl/sonLibCache.c
taffy/submodules/sonLib/C/impl/sonLibCommon.c
taffy/submodules/sonLib/C/impl/sonLibCompression.c
taffy/submodules/sonLib/C/impl/sonLibConnectivity.c
taffy/submodules/sonLib/C/impl/sonLibEulerTour.c
taffy/submodules/sonLib/C/impl/sonLibExcept.c
taffy/submodules/sonLib/C/impl/sonLibFile.c
taffy/submodules/sonLib/C/impl/sonLibGlobalsInternal.h
taffy/submodules/sonLib/C/impl/sonLibHash.c
taffy/submodules/sonLib/C/impl/sonLibKVDatabase.c
taffy/submodules/sonLib/C/impl/sonLibKVDatabaseConf.c
taffy/submodules/sonLib/C/impl/sonLibKVDatabasePrivate.h
taffy/submodules/sonLib/C/impl/sonLibKVDatabase_BigRecordFile.c
taffy/submodules/sonLib/C/impl/sonLibKVDatabase_MySql.c
taffy/submodules/sonLib/C/impl/sonLibKVDatabase_Redis.c
taffy/submodules/sonLib/C/impl/sonLibKVDatabase_TokyoCabinet.c
taffy/submodules/sonLib/C/impl/sonLibList.c
taffy/submodules/sonLib/C/impl/sonLibListPrivate.h
taffy/submodules/sonLib/C/impl/sonLibMath.c
taffy-0.0.3.dist-info/LICENSE
taffy-0.0.3.dist-info/METADATA
taffy-0.0.3.dist-info/WHEEL
taffy-0.0.3.dist-info/top_level.txt
taffy-0.0.3.dist-info/RECORD
