Metadata-Version: 2.1
Name: taffy
Version: 0.0.3
Summary: For manipulating taf and maf format alignments
Author-email: Benedict Paten <bpaten@ucsc.edu>, Glenn Hickey <glenn.hickey@gmail.com>
Project-URL: Homepage, https://github.com/ComparativeGenomicsToolkit/taffy
Project-URL: Bug Tracker, https://github.com/ComparativeGenomicsToolkit/taffy/issues
Classifier: Programming Language :: Python :: 3
Classifier: License :: OSI Approved :: MIT License
Classifier: Operating System :: OS Independent
Requires-Python: >=3.7
License-File: LICENSE
Requires-Dist: cffi >=1.0.0
Requires-Dist: numpy
Requires-Dist: torch
